be_llm101/__init__.py
be_llm101/info.py
be_llm101/data/IT_survey.csv
be_llm101/utils/__init__.py
be_llm101/utils/data.py
be_llm101/data/IT_survey.csv
be_llm101-0.1.5.dist-info/METADATA
be_llm101-0.1.5.dist-info/WHEEL
be_llm101-0.1.5.dist-info/RECORD
