Metadata-Version: 2.4
Name: be-llm101
Version: 0.1.5
Summary: A Python package for a BearingPoint internal LLM course
Project-URL: Homepage, https://github.com/yourusername/be-llm101
Project-URL: Repository, https://github.com/yourusername/be-llm101
Project-URL: Issues, https://github.com/yourusername/be-llm101/issues
Author-email: Eline and Kaspara <your.email@example.com>
License: MIT
Keywords: ai,llm,machine-learning,utilities
Classifier: Development Status :: 3 - Alpha
Classifier: Intended Audience :: Developers
Classifier: License :: OSI Approved :: MIT License
Classifier: Programming Language :: Python :: 3
Classifier: Programming Language :: Python :: 3.13
Requires-Python: >=3.11.12
Requires-Dist: devtools>=0.12.2
Requires-Dist: langchain-core>=0.3.35
Requires-Dist: langchain-openai>=0.3.6
Requires-Dist: openpyxl>=3.1.5
Requires-Dist: python-dotenv>=1.0.1
